clairvoyance/__init__.py
clairvoyance/settings.toml
clairvoyance/voyance.py
clairvoyance/notifiers/__init__.py
clairvoyance/notifiers/notifier.py
clairvoyance/notifiers/pubsub.py
clairvoyance/notifiers/sns.py
clairvoyance/notifiers/stdout.py
clairvoyance/notifiers/trivy_table.py
clairvoyance/reporters/__init__.py
clairvoyance/reporters/ecr.py
clairvoyance/reporters/ecr_native.py
clairvoyance/reporters/ecr_trivy.py
clairvoyance/reporters/reporter.py
voyance-1.0.3.dist-info/METADATA
voyance-1.0.3.dist-info/WHEEL
voyance-1.0.3.dist-info/entry_points.txt
voyance-1.0.3.dist-info/top_level.txt
voyance-1.0.3.dist-info/RECORD
