Metadata-Version: 2.4
Name: voyance
Version: 1.0.3
Requires-Dist: dynaconf<3.2,>=3.1
Requires-Dist: colorlog==6.7.0
Requires-Dist: boto3==1.26.61
Requires-Dist: click==8.1.3
Requires-Dist: backoff==2.2.1
Requires-Dist: google-cloud-pubsub==2.28.0
Provides-Extra: tests
Requires-Dist: tox; extra == "tests"
Requires-Dist: black<24,>=23.1.0; extra == "tests"
Requires-Dist: click==8.1.3; extra == "tests"
Requires-Dist: coverage-badge==1.0.1; extra == "tests"
Requires-Dist: coverage==7.1.0; extra == "tests"
Requires-Dist: flake8; extra == "tests"
Requires-Dist: isort; extra == "tests"
Requires-Dist: moto<5.0; extra == "tests"
Requires-Dist: pytest-cov>=4.0.0; extra == "tests"
Requires-Dist: pytest-datafiles>=2.0.1; extra == "tests"
Requires-Dist: pytest-env>=0.8.1; extra == "tests"
Requires-Dist: pytest-logger>=0.5.1; extra == "tests"
Requires-Dist: pytest-datafiles<=2.0.1; extra == "tests"
Requires-Dist: pytest-mock>=3.10.0; extra == "tests"
Requires-Dist: pytest-runner>=6.0.0; extra == "tests"
Requires-Dist: pytest-xdist>=3.1.0; extra == "tests"
Requires-Dist: pytest-lazy-fixture<0.7,>=0.6.3; extra == "tests"
Requires-Dist: pytest-sugar>=0.9.4; extra == "tests"
Requires-Dist: pytest<8,>=7.2.1; extra == "tests"
Dynamic: description
Dynamic: description-content-type
Dynamic: provides-extra
Dynamic: requires-dist
